odoo/addons/test_configuration_helper/README.rst
odoo/addons/test_configuration_helper/__init__.py
odoo/addons/test_configuration_helper/__manifest__.py
odoo/addons/test_configuration_helper/models.py
odoo/addons/test_configuration_helper/i18n/am.po
odoo/addons/test_configuration_helper/i18n/ca.po
odoo/addons/test_configuration_helper/i18n/de.po
odoo/addons/test_configuration_helper/i18n/el_GR.po
odoo/addons/test_configuration_helper/i18n/es.po
odoo/addons/test_configuration_helper/i18n/fi.po
odoo/addons/test_configuration_helper/i18n/fr.po
odoo/addons/test_configuration_helper/i18n/gl.po
odoo/addons/test_configuration_helper/i18n/hr.po
odoo/addons/test_configuration_helper/i18n/hr_HR.po
odoo/addons/test_configuration_helper/i18n/it.po
odoo/addons/test_configuration_helper/i18n/nl.po
odoo/addons/test_configuration_helper/i18n/pt.po
odoo/addons/test_configuration_helper/i18n/pt_BR.po
odoo/addons/test_configuration_helper/i18n/sl.po
odoo/addons/test_configuration_helper/i18n/test_configuration_helper.pot
odoo/addons/test_configuration_helper/i18n/tr.po
odoo/addons/test_configuration_helper/i18n/zh_CN.po
odoo/addons/test_configuration_helper/static/description/icon.png
odoo/addons/test_configuration_helper/tests/__init__.py
odoo/addons/test_configuration_helper/tests/test_config.py
odoo11_addon_test_configuration_helper-11.0.1.0.0.99.dev4.dist-info/METADATA
odoo11_addon_test_configuration_helper-11.0.1.0.0.99.dev4.dist-info/RECORD
odoo11_addon_test_configuration_helper-11.0.1.0.0.99.dev4.dist-info/WHEEL
odoo11_addon_test_configuration_helper-11.0.1.0.0.99.dev4.dist-info/top_level.txt
